vllm_sdk/__init__.py
vllm_sdk/chat.py
vllm_sdk/client.py
vllm_sdk/config.py
vllm_sdk/exceptions.py
vllm_sdk/features.py
vllm_sdk/schemas.py
vllm_sdk/utils.py
vllm_sdk/variant.py
vllm_sdk-0.2.0.dist-info/METADATA
vllm_sdk-0.2.0.dist-info/WHEEL
vllm_sdk-0.2.0.dist-info/top_level.txt
vllm_sdk-0.2.0.dist-info/RECORD
