Metadata-Version: 2.4
Name: vllm-sdk
Version: 0.2.0
Summary: Minimal Python SDK for the vLLM API
Author: vLLM Team
License: Apache-2.0
Project-URL: Homepage, https://github.com/agencyenterprise/vllm-sae
Project-URL: Documentation, https://github.com/agencyenterprise/vllm-sae
Project-URL: Repository, https://github.com/agencyenterprise/vllm-sae
Project-URL: Issues, https://github.com/agencyenterprise/vllm-sae/issues
Classifier: Development Status :: 4 - Beta
Classifier: Intended Audience :: Developers
Classifier: License :: OSI Approved :: Apache Software License
Classifier: Programming Language :: Python :: 3
Classifier: Programming Language :: Python :: 3.9
Classifier: Programming Language :: Python :: 3.10
Classifier: Programming Language :: Python :: 3.11
Classifier: Topic :: Software Development :: Libraries :: Python Modules
Classifier: Topic :: Scientific/Engineering :: Artificial Intelligence
Requires-Python: >=3.9
Requires-Dist: httpx>=0.24.0
Requires-Dist: pydantic>=2.0.0
Requires-Dist: python-dotenv>=1.0.0
